[
  {
    "name": "Alice",
    "scores": [
      85,
      90,
      78
    ]
  },
  {
    "name": "Bob",
    "scores": [
      70,
      88,
      84
    ]
  },
  {
    "name": "Charlie",
    "scores": [
      70,
      88,
      84
    ]
  },
  {
    "name": "Diana",
    "scores": [
      100,
      95,
      100
    ]
  },
  {
    "name": "laeXmm",
    "scores": [
      61,
      13,
      99
    ]
  },
  {
    "name": "RruKWI",
    "scores": [
      55,
      89,
      45,
      34
    ]
  },
  {
    "name": "Qacmspj",
    "scores": [20]
  },
  {
    "name": "YnxynR",
    "scores": [
      88,
      75,
      28
    ]
  },
  {
    "name": "quQgMJT",
    "scores": [
      62,
      76
    ]
  },
  {
    "name": "xLbfcfOfmg",
    "scores": [
      54
    ]
  },
  {
    "name": "ZNpJV",
    "scores": [
      55,
      4,
      31,
      31,
      79
    ]
  },
  {
    "name": "mxuRyXG",
    "scores": [
      64,
      58,
      94,
      5
    ]
  },
  {
    "name": "GCeudR",
    "scores": [
      63,
      96,
      96,
      29
    ]
  },
  {
    "name": "asZAabwN",
    "scores": [
      79,
      39
    ]
  },
  {
    "name": "dOTjzkIES",
    "scores": [10]
  },
  {
    "name": "RPNwZTmOM",
    "scores": [
      78,
      55,
      29
    ]
  },
  {
    "name": "AfwWT",
    "scores": [
      30,
      88,
      48,
      86
    ]
  },
  {
    "name": "eiRBpJnv",
    "scores": [
      13
    ]
  },
  {
    "name": "mZjkEJVqJB",
    "scores": [
      80
    ]
  },
  {
    "name": "CRQfueSXO",
    "scores": [
      31,
      99
    ]
  },
  {
    "name": "jjClleCYk",
    "scores": [
      78,
      62,
      53
    ]
  },
  {
    "name": "oXHSSvlkC",
    "scores": [
      63,
      82
    ]
  },
  {
    "name": "XvxIRuGoi",
    "scores": [
      59,
      33
    ]
  },
  {
    "name": "QKSkvvVo",
    "scores": [
      14,
      40,
      43,
      41
    ]
  },
  {
    "name": "ZicvcYAnsv",
    "scores": [
      96
    ]
  },
  {
    "name": "OREOA",
    "scores": [
      47,
      5,
      5,
      28,
      30
    ]
  },
  {
    "name": "tErbSDSTN",
    "scores": [
      46,
      69,
      100,
      92
    ]
  },
  {
    "name": "zBCiGiiNLu",
    "scores": [
      53,
      55,
      34,
      23
    ]
  },
  {
    "name": "ApwsDU",
    "scores": [
      43,
      42,
      79,
      25
    ]
  },
  {
    "name": "yZbfWpdxk",
    "scores": [
      39
    ]
  },
  {
    "name": "fdAJxLaow",
    "scores": [
      22
    ]
  },
  {
    "name": "YDSDKSFea",
    "scores": [
      7,
      41,
      67,
      19
    ]
  },
  {
    "name": "nbsBesjF",
    "scores": [
      49,
      10,
      25
    ]
  },
  {
    "name": "THSEhoe",
    "scores": [
      57
    ]
  },
  {
    "name": "TnGxeqSSbw",
    "scores": [
      74,
      50,
      41,
      81
    ]
  },
  {
    "name": "VcieiPEPfv",
    "scores": [
      99,
      30,
      10,
      55,
      96
    ]
  },
  {
    "name": "GlEtxRVkDp",
    "scores": [
      81
    ]
  },
  {
    "name": "xxqtXSE",
    "scores": [
      48,
      100,
      56,
      71
    ]
  },
  {
    "name": "DbrlN",
    "scores": [
      91,
      43,
      91,
      75
    ]
  },
  {
    "name": "APNbn",
    "scores": [
      26,
      63,
      62,
      35
    ]
  },
  {
    "name": "GmYuxvsUtR",
    "scores": [
      89,
      11,
      98,
      9
    ]
  },
  {
    "name": "ivBDtJvJ",
    "scores": [
      66,
      69,
      10,
      27
    ]
  },
  {
    "name": "LFrUxVM",
    "scores": []
  },
  {
    "name": "oEfhBCEkUf",
    "scores": [
      73,
      58,
      94
    ]
  },
  {
    "name": "YrEmdirtw",
    "scores": [
      43,
      48
    ]
  },
  {
    "name": "EYwnZI",
    "scores": []
  },
  {
    "name": "bDJleTpWp",
    "scores": [
      58,
      0,
      7,
      87
    ]
  },
  {
    "name": "APxlEWFOds",
    "scores": [
      55,
      95,
      78,
      40,
      25
    ]
  },
  {
    "name": "ufzJcpCAPV",
    "scores": [
      78
    ]
  },
  {
    "name": "IwYfSnQQc",
    "scores": [
      15,
      85,
      75
    ]
  },
  {
    "name": "zEJioO",
    "scores": [
      100,
      42
    ]
  },
  {
    "name": "gkFrLU",
    "scores": [
      45
    ]
  },
  {
    "name": "pAFqlfcJ",
    "scores": [
      66,
      13,
      80,
      14,
      38
    ]
  },
  {
    "name": "bKIfo",
    "scores": [
      80,
      77
    ]
  },
  {
    "name": "WeRXQ",
    "scores": [
      53,
      7,
      54
    ]
  },
  {
    "name": "RRngnOqVx",
    "scores": [
      85,
      70,
      17
    ]
  },
  {
    "name": "LTgzdYUY",
    "scores": [
      72,
      48,
      14
    ]
  },
  {
    "name": "YfGRZr",
    "scores": []
  },
  {
    "name": "lHRnHibk",
    "scores": [
      80,
      52
    ]
  },
  {
    "name": "NrfZHHs",
    "scores": [
      42,
      93,
      96,
      6
    ]
  },
  {
    "name": "ZMiwifCCR",
    "scores": [
      6,
      25
    ]
  },
  {
    "name": "QqMVHtAni",
    "scores": [
      7,
      40
    ]
  },
  {
    "name": "dzobkdj",
    "scores": []
  },
  {
    "name": "rZIybpR",
    "scores": [
      97,
      19,
      44,
      16
    ]
  },
  {
    "name": "HdaHAPrsq",
    "scores": [
      59,
      79
    ]
  },
  {
    "name": "rXvbz",
    "scores": [
      5,
      23
    ]
  },
  {
    "name": "NbnvoXWR",
    "scores": [
      75,
      83,
      39
    ]
  },
  {
    "name": "AqtGYZfcYA",
    "scores": []
  },
  {
    "name": "QJwnhGxpb",
    "scores": [
      99
    ]
  },
  {
    "name": "NloqAH",
    "scores": [
      53,
      48,
      65,
      87,
      67
    ]
  },
  {
    "name": "lxFuYJRCcN",
    "scores": [
      43,
      60,
      5,
      78,
      91
    ]
  },
  {
    "name": "nOHSEijFO",
    "scores": [
      61
    ]
  },
  {
    "name": "UwbpUdLfT",
    "scores": [
      84,
      51,
      46
    ]
  },
  {
    "name": "wpOnJp",
    "scores": [
      20,
      29,
      96
    ]
  },
  {
    "name": "GxyVJpIu",
    "scores": [
      83,
      99,
      56
    ]
  },
  {
    "name": "EvbGVIA",
    "scores": [
      35
    ]
  },
  {
    "name": "snfTOobnqz",
    "scores": []
  },
  {
    "name": "zowitbrZ",
    "scores": [
      47,
      63,
      12
    ]
  },
  {
    "name": "hxDMB",
    "scores": [
      70,
      9,
      13,
      62
    ]
  },
  {
    "name": "MAXYeYul",
    "scores": [
      20,
      34,
      97
    ]
  },
  {
    "name": "rfQKbrNtv",
    "scores": [
      68,
      2
    ]
  },
  {
    "name": "BApMnQph",
    "scores": [
      56
    ]
  },
  {
    "name": "dnQSBXVB",
    "scores": [
      29,
      92,
      32,
      5,
      97
    ]
  },
  {
    "name": "CfUXBu",
    "scores": [
      32
    ]
  },
  {
    "name": "WsvXJlD",
    "scores": [
      82,
      20,
      98
    ]
  },
  {
    "name": "GABlghwFWN",
    "scores": [
      42,
      46,
      75,
      72,
      49
    ]
  },
  {
    "name": "gLuZmAGcTD",
    "scores": [
      54
    ]
  },
  {
    "name": "pPSgy",
    "scores": [
      43,
      10,
      61,
      50
    ]
  },
  {
    "name": "YGkBP",
    "scores": []
  },
  {
    "name": "yjkFLbZxsf",
    "scores": [
      68,
      23,
      21,
      68,
      89
    ]
  },
  {
    "name": "Iawwo",
    "scores": [
      93
    ]
  },
  {
    "name": "YnxzrxKDx",
    "scores": [
      94,
      70,
      13,
      1,
      42
    ]
  },
  {
    "name": "INELIg",
    "scores": [
      24,
      62,
      65
    ]
  },
  {
    "name": "UMTQwnWO",
    "scores": [
      80,
      82
    ]
  },
  {
    "name": "jfdjQtdKTK",
    "scores": [
      34,
      30
    ]
  },
  {
    "name": "KwwhIu",
    "scores": [
      62,
      53,
      13
    ]
  },
  {
    "name": "gtvfdagGvL",
    "scores": []
  },
  {
    "name": "bxNmyEgFw",
    "scores": []
  },
  {
    "name": "VzoLREjJQV",
    "scores": [
      57,
      2,
      97
    ]
  },
  {
    "name": "jiwmrN",
    "scores": [
      82,
      49,
      9,
      54,
      87
    ]
  },
  {
    "name": "dgwuuh",
    "scores": [
      66,
      44,
      8,
      68,
      51
    ]
  },
  {
    "name": "OPSdGc",
    "scores": [
      58,
      43,
      59,
      83
    ]
  },
  {
    "name": "pQvuM",
    "scores": [
      45
    ]
  },
  {
    "name": "GXkvjEyf",
    "scores": [
      72,
      3,
      62
    ]
  },
  {
    "name": "IIcHTqLBk",
    "scores": [
      66,
      64,
      85,
      68
    ]
  },
  {
    "name": "deWkwTleb",
    "scores": [
      99,
      88,
      94
    ]
  },
  {
    "name": "ACSRhjpRmf",
    "scores": [
      62,
      61
    ]
  },
  {
    "name": "WaQLm",
    "scores": [
      33,
      34,
      32,
      32
    ]
  },
  {
    "name": "OgiOhXK",
    "scores": [
      1,
      58,
      65,
      37
    ]
  },
  {
    "name": "TbagiMzhPu",
    "scores": []
  },
  {
    "name": "OTUqG",
    "scores": []
  },
  {
    "name": "hhKaDtyx",
    "scores": [
      33,
      3,
      79
    ]
  },
  {
    "name": "BibfnnF",
    "scores": [
      76,
      15,
      49,
      39
    ]
  },
  {
    "name": "SurAvdduAl",
    "scores": [
      86,
      15,
      59
    ]
  },
  {
    "name": "ZrAsdVR",
    "scores": [
      5,
      56
    ]
  },
  {
    "name": "TpJvizyWTv",
    "scores": [
      91,
      23,
      84
    ]
  },
  {
    "name": "yQqdKVl",
    "scores": [
      84,
      22
    ]
  },
  {
    "name": "taCLhr",
    "scores": []
  },
  {
    "name": "iyNTIUBs",
    "scores": [
      59
    ]
  },
  {
    "name": "odRUstK",
    "scores": [
      48,
      44,
      96
    ]
  },
  {
    "name": "bjAOMc",
    "scores": [
      31
    ]
  },
  {
    "name": "tdyshHm",
    "scores": [
      77,
      97,
      3,
      91
    ]
  },
  {
    "name": "tPhsxBfb",
    "scores": [
      19
    ]
  },
  {
    "name": "oNPALJvYV",
    "scores": []
  },
  {
    "name": "VKLnqHEVEJ",
    "scores": [
      48,
      44
    ]
  },
  {
    "name": "UEWfA",
    "scores": [
      34,
      3,
      89
    ]
  },
  {
    "name": "NJUfy",
    "scores": [
      43
    ]
  },
  {
    "name": "dDiSfga",
    "scores": [
      31,
      99,
      36,
      32,
      98
    ]
  },
  {
    "name": "sLwPn",
    "scores": []
  },
  {
    "name": "gmsppKe",
    "scores": [
      95,
      70,
      66,
      3
    ]
  },
  {
    "name": "cmqnub",
    "scores": [
      26,
      74,
      96,
      6
    ]
  },
  {
    "name": "PxUeoTwNb",
    "scores": [
      34,
      18,
      8
    ]
  },
  {
    "name": "snPSw",
    "scores": [
      82,
      2,
      25,
      15,
      28
    ]
  },
  {
    "name": "EJcmpessJ",
    "scores": [
      7,
      2,
      70,
      34,
      34
    ]
  },
  {
    "name": "DvgRTCLLk",
    "scores": [
      7,
      46,
      75,
      69,
      100
    ]
  },
  {
    "name": "ajWnb",
    "scores": [
      11,
      33,
      36,
      4,
      50
    ]
  },
  {
    "name": "ioENTcJhJz",
    "scores": []
  },
  {
    "name": "orKVXyb",
    "scores": [
      100,
      41,
      95,
      35
    ]
  },
  {
    "name": "HupfXaxeH",
    "scores": [
      22,
      20
    ]
  },
  {
    "name": "tlyoL",
    "scores": [
      2,
      27,
      22
    ]
  },
  {
    "name": "kNVhkQ",
    "scores": []
  },
  {
    "name": "gUCTOp",
    "scores": [
      8
    ]
  },
  {
    "name": "xaJYfpT",
    "scores": [
      92,
      54
    ]
  },
  {
    "name": "ZdszXnCw",
    "scores": [
      92
    ]
  },
  {
    "name": "YRrfSs",
    "scores": [
      5
    ]
  },
  {
    "name": "UthkOdUI",
    "scores": [
      86,
      69,
      93
    ]
  },
  {
    "name": "KaSFO",
    "scores": []
  },
  {
    "name": "xaHQaRH",
    "scores": [
      78
    ]
  },
  {
    "name": "azCpsM",
    "scores": []
  },
  {
    "name": "nCsmPL",
    "scores": [
      41,
      52,
      57,
      99
    ]
  },
  {
    "name": "ADtOI",
    "scores": [
      84,
      60
    ]
  },
  {
    "name": "NmRzfjVaS",
    "scores": [
      94,
      64,
      47,
      25,
      79
    ]
  },
  {
    "name": "gMabhgCUX",
    "scores": [
      2
    ]
  },
  {
    "name": "daofYqje",
    "scores": [
      16,
      39,
      55,
      92,
      63
    ]
  },
  {
    "name": "jqJZdkbSh",
    "scores": [
      25,
      10
    ]
  },
  {
    "name": "KLzBjnOH",
    "scores": [
      55,
      63
    ]
  },
  {
    "name": "FsXOp",
    "scores": [
      35,
      40
    ]
  },
  {
    "name": "ytAtzwC",
    "scores": []
  },
  {
    "name": "TCIfR",
    "scores": [
      8,
      43,
      32
    ]
  },
  {
    "name": "aNhusYG",
    "scores": [
      46,
      70,
      71,
      56,
      82
    ]
  },
  {
    "name": "XRNkgpXWig",
    "scores": [
      36,
      14,
      78
    ]
  },
  {
    "name": "ITsfCRQz",
    "scores": [
      0
    ]
  },
  {
    "name": "zfPlKJrIU",
    "scores": [
      58,
      9,
      6
    ]
  },
  {
    "name": "bkcHUErsDR",
    "scores": [
      48,
      36,
      61,
      83,
      89
    ]
  },
  {
    "name": "cIMFaYeqM",
    "scores": [
      55,
      63,
      5
    ]
  },
  {
    "name": "rLhMn",
    "scores": [
      77,
      28,
      91,
      56,
      17
    ]
  },
  {
    "name": "eGDAk",
    "scores": [
      35,
      98,
      49,
      77
    ]
  },
  {
    "name": "ZABjuGQC",
    "scores": [
      16,
      77
    ]
  },
  {
    "name": "KmOCaT",
    "scores": [
      56
    ]
  },
  {
    "name": "jkKaoLSDC",
    "scores": [
      37,
      68,
      6
    ]
  },
  {
    "name": "HuzeVBuc",
    "scores": [
      86,
      99,
      2
    ]
  },
  {
    "name": "FwGxIy",
    "scores": [
      10
    ]
  },
  {
    "name": "XFnPlpB",
    "scores": [
      3,
      22
    ]
  },
  {
    "name": "WqTBFqvzpF",
    "scores": [
      95,
      75,
      89
    ]
  },
  {
    "name": "bfeaLosI",
    "scores": [
      32,
      26,
      40,
      41,
      99
    ]
  },
  {
    "name": "tyIjobxG",
    "scores": [
      72,
      1,
      83,
      65,
      16
    ]
  },
  {
    "name": "oUvkcw",
    "scores": [
      95,
      68,
      10,
      54
    ]
  },
  {
    "name": "YshkxBYwHS",
    "scores": [
      59,
      11,
      64
    ]
  },
  {
    "name": "bihEYSqhsr",
    "scores": [
      91,
      3,
      83,
      43
    ]
  },
  {
    "name": "DaHOtZi",
    "scores": [
      11
    ]
  },
  {
    "name": "lwYWSHasd",
    "scores": [
      22,
      76,
      7,
      45
    ]
  },
  {
    "name": "xFCBSRHzts",
    "scores": [
      100,
      17,
      83
    ]
  },
  {
    "name": "YYJSvMZO",
    "scores": [
      14,
      95,
      49,
      61,
      61
    ]
  },
  {
    "name": "tKxFFB",
    "scores": [
      7
    ]
  },
  {
    "name": "rXgCMxhqB",
    "scores": [
      86,
      26
    ]
  },
  {
    "name": "Ixttrlt",
    "scores": [
      89
    ]
  },
  {
    "name": "OpRPoPtWA",
    "scores": [
      99,
      8,
      51,
      88
    ]
  },
  {
    "name": "voHEBKW",
    "scores": [
      12,
      22,
      35,
      70
    ]
  },
  {
    "name": "DCHeTlIxa",
    "scores": [
      16,
      70,
      30
    ]
  },
  {
    "name": "LuxkRuT",
    "scores": [
      77,
      94,
      22,
      100
    ]
  },
  {
    "name": "dOjIDN",
    "scores": [
      23,
      28
    ]
  },
  {
    "name": "RuGiM",
    "scores": [
      73,
      20,
      47,
      53,
      91
    ]
  },
  {
    "name": "YoybRRLRl",
    "scores": [
      9,
      8,
      31,
      2,
      27
    ]
  },
  {
    "name": "AfeStBhVj",
    "scores": [
      5
    ]
  },
  {
    "name": "GrTGf",
    "scores": [
      81,
      3
    ]
  },
  {
    "name": "thcOSRvbQB",
    "scores": [
      35,
      75,
      74,
      85,
      8
    ]
  },
  {
    "name": "tEpXdnY",
    "scores": []
  },
  {
    "name": "aeSjLIooh",
    "scores": [
      15,
      83,
      48
    ]
  },
  {
    "name": "dNwbNGe",
    "scores": []
  },
  {
    "name": "JYEZCkCJ",
    "scores": [
      2
    ]
  },
  {
    "name": "camLFD",
    "scores": [
      54,
      33
    ]
  },
  {
    "name": "oxFORmJj",
    "scores": [
      39,
      79,
      78,
      50,
      80
    ]
  },
  {
    "name": "ShhTSt",
    "scores": [
      34,
      82,
      80
    ]
  },
  {
    "name": "MWCnI",
    "scores": [
      20,
      91,
      21,
      45
    ]
  },
  {
    "name": "bvCWRXAwL",
    "scores": []
  },
  {
    "name": "KtmfaJU",
    "scores": []
  },
  {
    "name": "VxflUEduGh",
    "scores": [
      40
    ]
  },
  {
    "name": "qCSiRTQFqV",
    "scores": [
      12,
      90
    ]
  },
  {
    "name": "FmvIcBE",
    "scores": [
      100,
      29,
      57
    ]
  },
  {
    "name": "lZwmpZB",
    "scores": [
      51,
      15,
      15
    ]
  },
  {
    "name": "hNHvaFP",
    "scores": [
      94,
      48,
      56
    ]
  },
  {
    "name": "dHeylhnlbn",
    "scores": [
      76,
      7,
      62,
      37,
      44
    ]
  },
  {
    "name": "zFfjzPqFSC",
    "scores": [
      41,
      70,
      12,
      42,
      56
    ]
  },
  {
    "name": "MVYlCaBu",
    "scores": [
      11,
      18,
      23,
      29
    ]
  },
  {
    "name": "zrHig",
    "scores": []
  },
  {
    "name": "OveHKjLnuD",
    "scores": [
      56,
      46,
      3,
      69,
      15
    ]
  },
  {
    "name": "jRtUukqGp",
    "scores": [
      81,
      19,
      95,
      65
    ]
  },
  {
    "name": "wjywh",
    "scores": [
      55,
      83,
      78,
      90,
      46
    ]
  },
  {
    "name": "WDALtQkO",
    "scores": [
      4,
      26,
      72,
      70
    ]
  },
  {
    "name": "iXZnU",
    "scores": [
      42,
      34,
      69
    ]
  },
  {
    "name": "ZYdRI",
    "scores": [
      36,
      52
    ]
  },
  {
    "name": "sfSVQqGE",
    "scores": []
  },
  {
    "name": "PIbgSwz",
    "scores": [
      35,
      18,
      76
    ]
  },
  {
    "name": "zseCVH",
    "scores": [
      43,
      21
    ]
  },
  {
    "name": "JtEExH",
    "scores": [
      27,
      25
    ]
  },
  {
    "name": "ZZMll",
    "scores": [
      8
    ]
  },
  {
    "name": "IEOMbGlv",
    "scores": [
      13,
      60,
      69,
      64,
      72
    ]
  },
  {
    "name": "apmAeKkOwP",
    "scores": [
      74,
      82,
      60,
      34,
      74
    ]
  },
  {
    "name": "mkIRnq",
    "scores": [
      4,
      30
    ]
  },
  {
    "name": "zshsNp",
    "scores": [
      85,
      44,
      53
    ]
  },
  {
    "name": "yiKRfcvF",
    "scores": [
      0,
      28
    ]
  },
  {
    "name": "gBJFeCGGLm",
    "scores": [
      69,
      22,
      92,
      59,
      39
    ]
  },
  {
    "name": "RsYuGc",
    "scores": []
  },
  {
    "name": "QAwFA",
    "scores": [
      28
    ]
  },
  {
    "name": "YizfWlKmCr",
    "scores": [
      89,
      85,
      2,
      43,
      58
    ]
  },
  {
    "name": "EqWQql",
    "scores": [
      40,
      81
    ]
  },
  {
    "name": "XBzpL",
    "scores": []
  },
  {
    "name": "MtaDm",
    "scores": [
      71,
      67,
      58,
      94,
      69
    ]
  },
  {
    "name": "JTWJihwr",
    "scores": [
      46
    ]
  },
  {
    "name": "vJtssLnm",
    "scores": []
  },
  {
    "name": "QxBBOsbsv",
    "scores": [
      71
    ]
  },
  {
    "name": "tikTPljsHt",
    "scores": [
      76,
      89,
      44,
      17
    ]
  },
  {
    "name": "kKwEkbl",
    "scores": [
      54,
      2
    ]
  },
  {
    "name": "sCbwl",
    "scores": [
      32,
      2,
      91
    ]
  },
  {
    "name": "meQDV",
    "scores": [
      13,
      72
    ]
  },
  {
    "name": "EkibGXaHPo",
    "scores": [
      92,
      64,
      44
    ]
  },
  {
    "name": "rpTEzIxqU",
    "scores": []
  },
  {
    "name": "iZNwBFmBS",
    "scores": [
      22
    ]
  },
  {
    "name": "avtIWA",
    "scores": [
      12
    ]
  },
  {
    "name": "TnznSylik",
    "scores": [
      80,
      80,
      54
    ]
  },
  {
    "name": "STbAgXEGR",
    "scores": []
  },
  {
    "name": "AhXQDYGg",
    "scores": [
      0
    ]
  },
  {
    "name": "IwTyoxWNfO",
    "scores": [
      21,
      69
    ]
  },
  {
    "name": "AQzUhgIlt",
    "scores": [
      74,
      48
    ]
  },
  {
    "name": "SrYXGmWNZ",
    "scores": [
      10,
      92,
      41,
      55
    ]
  },
  {
    "name": "UBpJGtM",
    "scores": [
      26,
      73,
      32,
      71,
      15
    ]
  },
  {
    "name": "DAxnYVG",
    "scores": []
  },
  {
    "name": "NQXFGQ",
    "scores": []
  },
  {
    "name": "cJCCIGy",
    "scores": []
  },
  {
    "name": "BUasZIee",
    "scores": [
      70,
      30,
      84,
      91
    ]
  },
  {
    "name": "DklLE",
    "scores": [
      83
    ]
  },
  {
    "name": "ZgXEdk",
    "scores": []
  },
  {
    "name": "mrVIZT",
    "scores": [
      17,
      21,
      80
    ]
  },
  {
    "name": "LZCWLTklI",
    "scores": [
      31,
      68,
      77,
      1
    ]
  },
  {
    "name": "LgDSuFln",
    "scores": []
  },
  {
    "name": "DtEuijdW",
    "scores": [
      39,
      1,
      36,
      17
    ]
  },
  {
    "name": "OlZgVb",
    "scores": [
      85,
      22,
      81,
      27
    ]
  },
  {
    "name": "FTvpHQDmG",
    "scores": [
      5,
      91,
      98,
      46
    ]
  },
  {
    "name": "ktiQwTbe",
    "scores": [
      87,
      51,
      6,
      28
    ]
  },
  {
    "name": "GLjOsD",
    "scores": [
      44,
      19,
      98,
      34
    ]
  },
  {
    "name": "NlFkdLqBxC",
    "scores": [
      0,
      20,
      90,
      93
    ]
  },
  {
    "name": "EJQIjw",
    "scores": []
  },
  {
    "name": "LCkTjhMSA",
    "scores": [
      64,
      65,
      10,
      76,
      31
    ]
  },
  {
    "name": "XQcBbCAi",
    "scores": [
      75,
      15,
      19,
      41,
      22
    ]
  },
  {
    "name": "BlMLQf",
    "scores": [
      4,
      1,
      70,
      83
    ]
  },
  {
    "name": "CUVRvccSGJ",
    "scores": []
  },
  {
    "name": "fjyqD",
    "scores": [
      84,
      1
    ]
  },
  {
    "name": "xTuJAi",
    "scores": [
      64,
      54,
      29,
      0
    ]
  },
  {
    "name": "mXdysas",
    "scores": [
      33,
      46,
      85
    ]
  },
  {
    "name": "ZhwZx",
    "scores": []
  },
  {
    "name": "qynSzqTSM",
    "scores": []
  },
  {
    "name": "jhidmA",
    "scores": [
      15
    ]
  },
  {
    "name": "jJEkFVBxo",
    "scores": [
      98,
      41,
      51
    ]
  },
  {
    "name": "tzszjsQzjl",
    "scores": [
      60,
      5,
      80
    ]
  },
  {
    "name": "redNEtL",
    "scores": [
      67,
      85,
      30
    ]
  },
  {
    "name": "gioQnfcZH",
    "scores": [
      61,
      100,
      9,
      35
    ]
  },
  {
    "name": "cYqFcef",
    "scores": [
      91,
      61,
      35,
      13,
      96
    ]
  },
  {
    "name": "bihYQVSRCr",
    "scores": [
      98,
      56,
      14,
      85
    ]
  },
  {
    "name": "JuDRQXzHoU",
    "scores": []
  },
  {
    "name": "qxplC",
    "scores": [
      72,
      38,
      52
    ]
  },
  {
    "name": "CTUum",
    "scores": [
      20,
      96,
      51
    ]
  },
  {
    "name": "pVkjPZcHL",
    "scores": [
      30,
      20,
      57,
      57,
      77
    ]
  },
  {
    "name": "hKWWkpzGK",
    "scores": []
  },
  {
    "name": "KueLdvl",
    "scores": [
      36,
      66
    ]
  },
  {
    "name": "WYWaz",
    "scores": [
      21,
      22,
      63,
      99
    ]
  },
  {
    "name": "tzmFSIh",
    "scores": [
      72,
      38
    ]
  },
  {
    "name": "jFEzWhbkpY",
    "scores": [
      21,
      52,
      41
    ]
  },
  {
    "name": "FMBcJ",
    "scores": []
  },
  {
    "name": "HwKIjyirxS",
    "scores": [
      13,
      98,
      16,
      89,
      29
    ]
  },
  {
    "name": "esLarQMhe",
    "scores": [
      32,
      13,
      82
    ]
  },
  {
    "name": "IxFCGtRMC",
    "scores": []
  },
  {
    "name": "KdNibQAl",
    "scores": [
      14,
      13,
      72
    ]
  },
  {
    "name": "UsDLphwKV",
    "scores": [
      85
    ]
  },
  {
    "name": "Oqzvek",
    "scores": [
      13,
      94,
      40
    ]
  },
  {
    "name": "UPAhwy",
    "scores": [
      91,
      52,
      32,
      78
    ]
  },
  {
    "name": "gytpi",
    "scores": [
      45,
      15,
      33
    ]
  },
  {
    "name": "DQtZHkxhZ",
    "scores": [
      34,
      84,
      36,
      33,
      26
    ]
  },
  {
    "name": "bqyIgweZAO",
    "scores": [
      51,
      22,
      30,
      93,
      65
    ]
  },
  {
    "name": "iIQWFzg",
    "scores": [
      78,
      34,
      54,
      64
    ]
  },
  {
    "name": "SuavlqpdqB",
    "scores": [
      28,
      76
    ]
  },
  {
    "name": "FCKNWLup",
    "scores": [
      98
    ]
  },
  {
    "name": "ArJoXp",
    "scores": [
      45,
      59,
      52,
      76
    ]
  },
  {
    "name": "PvCjtHXJ",
    "scores": [
      66
    ]
  },
  {
    "name": "crDNJJXKA",
    "scores": [
      33,
      37,
      28,
      12,
      81
    ]
  },
  {
    "name": "CekJfFlCj",
    "scores": [
      52,
      7,
      10,
      28,
      21
    ]
  },
  {
    "name": "QokSsvGhqi",
    "scores": [
      99,
      99
    ]
  },
  {
    "name": "fSqxlih",
    "scores": []
  },
  {
    "name": "qVIOjYI",
    "scores": [
      18,
      22,
      9
    ]
  },
  {
    "name": "lyHLLxRT",
    "scores": [
      1
    ]
  },
  {
    "name": "lSsJp",
    "scores": [
      45,
      6,
      95
    ]
  },
  {
    "name": "IicaLHLTFd",
    "scores": [
      74
    ]
  },
  {
    "name": "RgQJMW",
    "scores": [
      4,
      28
    ]
  },
  {
    "name": "kCSOnnPD",
    "scores": [
      26,
      31,
      92,
      58
    ]
  },
  {
    "name": "siXoCquhzr",
    "scores": [
      63,
      81,
      19
    ]
  },
  {
    "name": "NaSaUEdY",
    "scores": [
      71,
      31,
      77,
      84
    ]
  },
  {
    "name": "uPWUtPm",
    "scores": [
      19,
      28,
      16
    ]
  },
  {
    "name": "CbZRFqSO",
    "scores": [
      90
    ]
  },
  {
    "name": "YSpDobop",
    "scores": [
      96,
      59
    ]
  },
  {
    "name": "DrlNFCjX",
    "scores": [
      64,
      46,
      23
    ]
  },
  {
    "name": "vyvzwkOF",
    "scores": [
      15
    ]
  },
  {
    "name": "feigKe",
    "scores": [
      50,
      100,
      12
    ]
  },
  {
    "name": "hUwLO",
    "scores": [
      60,
      28
    ]
  },
  {
    "name": "wsBGmicfya",
    "scores": [
      81,
      2,
      84,
      63,
      35
    ]
  },
  {
    "name": "kSculVkQxN",
    "scores": [
      79
    ]
  },
  {
    "name": "cAbzFc",
    "scores": [
      88,
      70
    ]
  },
  {
    "name": "GiImyB",
    "scores": []
  },
  {
    "name": "paYLSuHD",
    "scores": [
      46,
      27,
      72
    ]
  },
  {
    "name": "ceFjMd",
    "scores": [
      23,
      70,
      73,
      26
    ]
  },
  {
    "name": "nJBXOI",
    "scores": []
  },
  {
    "name": "XTkgGoNyk",
    "scores": [
      43,
      33,
      100,
      96
    ]
  },
  {
    "name": "sZWlnN",
    "scores": []
  },
  {
    "name": "TjpNMhP",
    "scores": []
  },
  {
    "name": "sIHCcVWQbS",
    "scores": [
      71,
      42,
      22,
      24,
      36
    ]
  },
  {
    "name": "UkAfYEvvnI",
    "scores": [
      3
    ]
  },
  {
    "name": "SRICnP",
    "scores": []
  },
  {
    "name": "pGJELbVbM",
    "scores": [
      9,
      69,
      82,
      90,
      73
    ]
  },
  {
    "name": "qjBCHPh",
    "scores": [
      81,
      28
    ]
  },
  {
    "name": "CXCOm",
    "scores": [
      71
    ]
  },
  {
    "name": "tSziHtLblv",
    "scores": []
  },
  {
    "name": "VDggiIKdn",
    "scores": []
  },
  {
    "name": "olPsVnx",
    "scores": [
      12
    ]
  },
  {
    "name": "KBJJo",
    "scores": [
      13
    ]
  },
  {
    "name": "bxrjwwH",
    "scores": [
      9,
      73
    ]
  },
  {
    "name": "gsIUadoN",
    "scores": [
      24,
      86,
      58,
      83
    ]
  },
  {
    "name": "sQahbUFrw",
    "scores": [
      25
    ]
  },
  {
    "name": "oyJMnIf",
    "scores": [
      45,
      72
    ]
  },
  {
    "name": "rsKRd",
    "scores": [
      94,
      53,
      42,
      14,
      32
    ]
  },
  {
    "name": "gKidjI",
    "scores": [
      55,
      100
    ]
  },
  {
    "name": "WfQkA",
    "scores": [
      51,
      65,
      62,
      23,
      29
    ]
  },
  {
    "name": "WbKBWgTfd",
    "scores": [
      91,
      26,
      75,
      36,
      27
    ]
  },
  {
    "name": "NsmctsaAVK",
    "scores": [
      49,
      4
    ]
  },
  {
    "name": "IrDCC",
    "scores": [
      56,
      12,
      6,
      8
    ]
  },
  {
    "name": "xIrCAETwfs",
    "scores": [
      53,
      57,
      32,
      25,
      12
    ]
  },
  {
    "name": "AqScn",
    "scores": [
      90
    ]
  },
  {
    "name": "eaOvVWS",
    "scores": [
      18
    ]
  },
  {
    "name": "dYNPPegm",
    "scores": [
      82
    ]
  },
  {
    "name": "gYYgZ",
    "scores": [
      86,
      4
    ]
  },
  {
    "name": "gKdIPvCkS",
    "scores": [
      20,
      21
    ]
  },
  {
    "name": "PdkYM",
    "scores": [
      56,
      88,
      37
    ]
  },
  {
    "name": "LeWVkiZiA",
    "scores": []
  },
  {
    "name": "aFTclNyJLo",
    "scores": [
      32,
      58,
      77
    ]
  },
  {
    "name": "vHAbctXOsa",
    "scores": []
  },
  {
    "name": "TsdRbxPFD",
    "scores": []
  },
  {
    "name": "zUejuC",
    "scores": [
      53
    ]
  },
  {
    "name": "AUknHc",
    "scores": [
      1,
      100
    ]
  },
  {
    "name": "FvdEgruc",
    "scores": [
      79,
      62,
      39
    ]
  },
  {
    "name": "gvfYdim",
    "scores": [
      67,
      58,
      83
    ]
  },
  {
    "name": "klNGL",
    "scores": [
      100,
      33,
      52
    ]
  },
  {
    "name": "tsUZG",
    "scores": []
  },
  {
    "name": "YYscpyAaA",
    "scores": [
      30,
      59,
      21
    ]
  },
  {
    "name": "uMDtPbx",
    "scores": []
  },
  {
    "name": "JcspqucEH",
    "scores": [
      37
    ]
  },
  {
    "name": "vqpFA",
    "scores": [
      38,
      71
    ]
  },
  {
    "name": "yUMAw",
    "scores": []
  },
  {
    "name": "vZOWmPIaLo",
    "scores": []
  },
  {
    "name": "QiPhzQNK",
    "scores": [
      62,
      24,
      7
    ]
  },
  {
    "name": "iFAmSy",
    "scores": [
      45
    ]
  },
  {
    "name": "yPZpV",
    "scores": [
      86,
      61
    ]
  },
  {
    "name": "DDJGIdt",
    "scores": [
      8,
      88
    ]
  },
  {
    "name": "ydJLt",
    "scores": []
  },
  {
    "name": "FfbKCOBmAL",
    "scores": [
      40,
      36,
      88,
      65,
      85
    ]
  },
  {
    "name": "qCNVVxloZ",
    "scores": []
  },
  {
    "name": "AGUjJGel",
    "scores": []
  },
  {
    "name": "ufHvbhc",
    "scores": [
      1,
      38
    ]
  },
  {
    "name": "MPatCxR",
    "scores": [
      87,
      8
    ]
  },
  {
    "name": "nARxevcgi",
    "scores": [
      33,
      86,
      66,
      97,
      70
    ]
  },
  {
    "name": "WQRdidp",
    "scores": []
  },
  {
    "name": "NymrHcN",
    "scores": [
      23,
      66,
      14,
      88
    ]
  },
  {
    "name": "BtyrvvYzm",
    "scores": [
      33,
      49,
      56,
      84,
      47
    ]
  },
  {
    "name": "UwCDvvrOJj",
    "scores": [
      11,
      40,
      19,
      19,
      60
    ]
  },
  {
    "name": "ovNBBdLE",
    "scores": [
      22,
      47,
      42,
      38,
      42
    ]
  },
  {
    "name": "JIFEcL",
    "scores": [
      57,
      59,
      14,
      51,
      84
    ]
  },
  {
    "name": "AXYpxR",
    "scores": [
      66,
      70,
      10
    ]
  },
  {
    "name": "PTwljYT",
    "scores": [
      96
    ]
  },
  {
    "name": "pvRoQAP",
    "scores": [
      26,
      86
    ]
  },
  {
    "name": "gkaalGEZs",
    "scores": []
  },
  {
    "name": "auOmb",
    "scores": [
      27,
      22,
      86,
      72,
      22
    ]
  },
  {
    "name": "bqFrI",
    "scores": [
      98,
      99,
      49
    ]
  },
  {
    "name": "OXxusus",
    "scores": [
      43,
      45,
      57
    ]
  },
  {
    "name": "GBKvyM",
    "scores": [
      80,
      67,
      23
    ]
  },
  {
    "name": "PpvTai",
    "scores": []
  },
  {
    "name": "BWDiGtvpCX",
    "scores": [
      80,
      87
    ]
  },
  {
    "name": "vRizw",
    "scores": [
      27,
      45,
      81
    ]
  },
  {
    "name": "WmNzhaGhp",
    "scores": [
      44,
      53,
      68,
      76
    ]
  },
  {
    "name": "OVyyXY",
    "scores": [
      49,
      96,
      36,
      5,
      84
    ]
  },
  {
    "name": "LLChwJlTyx",
    "scores": [
      88,
      10,
      85
    ]
  },
  {
    "name": "WMUoQOGvUT",
    "scores": [
      66,
      91,
      49
    ]
  },
  {
    "name": "BemPniHT",
    "scores": []
  },
  {
    "name": "LPTyFcl",
    "scores": [
      53,
      86,
      6
    ]
  },
  {
    "name": "DJXJe",
    "scores": [
      78,
      1,
      20,
      60
    ]
  },
  {
    "name": "NiXZltNauh",
    "scores": [
      19,
      2,
      61,
      63,
      22
    ]
  },
  {
    "name": "FdlTQGo",
    "scores": []
  },
  {
    "name": "THvrsn",
    "scores": [
      85
    ]
  },
  {
    "name": "WNWyAo",
    "scores": [
      37,
      83,
      21,
      0,
      77
    ]
  },
  {
    "name": "uVPuIAg",
    "scores": [
      46
    ]
  },
  {
    "name": "OClwK",
    "scores": [
      97
    ]
  },
  {
    "name": "GkyOWrT",
    "scores": [
      10,
      99
    ]
  },
  {
    "name": "POlBsN",
    "scores": [
      79,
      54,
      64,
      87
    ]
  },
  {
    "name": "GiPscJFsOl",
    "scores": [
      0,
      51
    ]
  },
  {
    "name": "nKJli",
    "scores": [
      40,
      24
    ]
  },
  {
    "name": "MAdnK",
    "scores": [
      34,
      20,
      97,
      57,
      90
    ]
  },
  {
    "name": "izHEVEkx",
    "scores": [
      47,
      26,
      81,
      69,
      35
    ]
  },
  {
    "name": "QCvWnue",
    "scores": [
      91,
      18,
      37,
      87
    ]
  },
  {
    "name": "IjoDzFdZa",
    "scores": []
  },
  {
    "name": "yfjezPnd",
    "scores": [
      92
    ]
  },
  {
    "name": "WiTzQ",
    "scores": []
  },
  {
    "name": "JgtAa",
    "scores": [
      39
    ]
  },
  {
    "name": "lKGHooQmI",
    "scores": [
      55,
      6
    ]
  },
  {
    "name": "JHanquiZq",
    "scores": [
      11,
      43,
      60
    ]
  },
  {
    "name": "AAlyS",
    "scores": [
      4,
      44,
      88,
      6,
      15
    ]
  },
  {
    "name": "YoYiSrEBz",
    "scores": []
  },
  {
    "name": "IyfCd",
    "scores": [
      30,
      35
    ]
  },
  {
    "name": "NaSeVZAUkt",
    "scores": [
      74,
      74,
      74,
      21
    ]
  },
  {
    "name": "NVAEfP",
    "scores": []
  },
  {
    "name": "SomxwLfQ",
    "scores": []
  },
  {
    "name": "ktmdQe",
    "scores": [
      11
    ]
  },
  {
    "name": "kMIgdxtGW",
    "scores": [
      19,
      61,
      87,
      24,
      25
    ]
  },
  {
    "name": "fHQwGnGT",
    "scores": [
      56,
      94,
      83,
      96,
      38
    ]
  },
  {
    "name": "nJhtRqgRS",
    "scores": []
  },
  {
    "name": "FUAhJxbKVe",
    "scores": [
      36
    ]
  },
  {
    "name": "OhPxj",
    "scores": [
      77,
      23,
      14,
      24,
      20
    ]
  },
  {
    "name": "DPPYCakLmr",
    "scores": [
      52,
      85,
      19,
      57
    ]
  },
  {
    "name": "faJTcp",
    "scores": [
      80
    ]
  },
  {
    "name": "MGiLJhOl",
    "scores": [
      55,
      70
    ]
  },
  {
    "name": "SJDuOsoc",
    "scores": [
      54,
      7,
      0,
      76,
      8
    ]
  },
  {
    "name": "VRnBOJB",
    "scores": [
      37,
      25
    ]
  },
  {
    "name": "vCZeab",
    "scores": [
      33,
      77,
      58,
      18
    ]
  },
  {
    "name": "ZoJmicT",
    "scores": [
      80,
      1,
      73
    ]
  },
  {
    "name": "klrlxqESKT",
    "scores": [
      41,
      77
    ]
  },
  {
    "name": "nBFNUitkZL",
    "scores": [
      20,
      47,
      69,
      62,
      60
    ]
  },
  {
    "name": "wsjXUerW",
    "scores": [
      37,
      78,
      94
    ]
  },
  {
    "name": "sHjShsX",
    "scores": [
      99,
      68
    ]
  },
  {
    "name": "huyZCPi",
    "scores": [
      96,
      85
    ]
  },
  {
    "name": "GiJGEDSZe",
    "scores": [
      94,
      29
    ]
  },
  {
    "name": "skPIch",
    "scores": [
      55,
      66,
      13,
      69,
      16
    ]
  },
  {
    "name": "MwGmD",
    "scores": [
      83
    ]
  },
  {
    "name": "iveXxSaL",
    "scores": [
      97,
      59,
      60
    ]
  },
  {
    "name": "dMQUiNSB",
    "scores": [
      21,
      69
    ]
  },
  {
    "name": "SxhVnt",
    "scores": []
  },
  {
    "name": "kDHDeX",
    "scores": [
      45,
      4,
      87,
      75,
      84
    ]
  },
  {
    "name": "zxmGDcs",
    "scores": [
      33,
      10,
      97,
      37
    ]
  },
  {
    "name": "kcsgEtrWmn",
    "scores": [
      95,
      59,
      33,
      41,
      92
    ]
  },
  {
    "name": "qOfckBfRCA",
    "scores": [
      3
    ]
  },
  {
    "name": "urEvjrz",
    "scores": [
      49,
      25,
      39
    ]
  },
  {
    "name": "WptIWDy",
    "scores": [
      65,
      97,
      45,
      84,
      17
    ]
  },
  {
    "name": "GKuFFgL",
    "scores": [
      18,
      53
    ]
  },
  {
    "name": "bzjdxu",
    "scores": [
      99,
      26,
      50,
      42
    ]
  },
  {
    "name": "fZpTClF",
    "scores": [
      2
    ]
  },
  {
    "name": "bNqLIG",
    "scores": []
  },
  {
    "name": "mnlauQbTG",
    "scores": [
      50,
      5,
      58,
      39
    ]
  },
  {
    "name": "ZetoOSJCb",
    "scores": [
      95
    ]
  },
  {
    "name": "PZTJOJSun",
    "scores": [
      87,
      45,
      67,
      51
    ]
  },
  {
    "name": "YVRxSYKCgn",
    "scores": [
      82,
      49,
      54,
      96,
      43
    ]
  },
  {
    "name": "BXPZVh",
    "scores": [
      58,
      100,
      56
    ]
  },
  {
    "name": "RaTopFHVQ",
    "scores": [
      86,
      32
    ]
  },
  {
    "name": "WYYtW",
    "scores": [
      43,
      18,
      8,
      10
    ]
  },
  {
    "name": "sZaTpZG",
    "scores": [
      48
    ]
  },
  {
    "name": "xireyAfYs",
    "scores": [
      4
    ]
  },
  {
    "name": "BQnTYhNVst",
    "scores": [
      85,
      65,
      97,
      81
    ]
  },
  {
    "name": "AvNVLQkj",
    "scores": []
  },
  {
    "name": "xECEzm",
    "scores": [
      44
    ]
  },
  {
    "name": "OzcOSLAHia",
    "scores": []
  },
  {
    "name": "aHBFyxAt",
    "scores": [
      36,
      89,
      50,
      0
    ]
  },
  {
    "name": "VJSuN",
    "scores": [
      96,
      35,
      8,
      19
    ]
  },
  {
    "name": "IhymTGgYzP",
    "scores": [
      13,
      92,
      45,
      39
    ]
  },
  {
    "name": "JgIYQ",
    "scores": []
  },
  {
    "name": "YyvkehHvv",
    "scores": [
      21,
      83
    ]
  },
  {
    "name": "yixGN",
    "scores": []
  },
  {
    "name": "mFTQJf",
    "scores": [
      16,
      59,
      91,
      2,
      33
    ]
  },
  {
    "name": "LAVsJOUdi",
    "scores": []
  },
  {
    "name": "HtaTllHRW",
    "scores": [
      6,
      54,
      63
    ]
  },
  {
    "name": "BVrHVMfbhp",
    "scores": [
      3,
      20,
      45,
      88,
      31
    ]
  },
  {
    "name": "VqoOYVzm",
    "scores": [
      13
    ]
  },
  {
    "name": "iEoVvA",
    "scores": []
  },
  {
    "name": "REyfwVfQ",
    "scores": [
      13
    ]
  },
  {
    "name": "VDXWn",
    "scores": [
      77
    ]
  },
  {
    "name": "thWbqqg",
    "scores": [
      59,
      38
    ]
  },
  {
    "name": "ylmQeNBB",
    "scores": [
      94,
      76,
      75,
      4,
      57
    ]
  },
  {
    "name": "UoDATuvAV",
    "scores": []
  },
  {
    "name": "QvHWwhou",
    "scores": [
      26,
      48,
      33
    ]
  },
  {
    "name": "dAcRqoO",
    "scores": []
  },
  {
    "name": "XnixWkG",
    "scores": [
      5,
      31,
      79,
      79
    ]
  },
  {
    "name": "ANrELJft",
    "scores": [
      59,
      29,
      5,
      7,
      14
    ]
  },
  {
    "name": "afAPfAdGQF",
    "scores": [
      13,
      52,
      75,
      45
    ]
  },
  {
    "name": "DVSXQH",
    "scores": [
      37,
      53
    ]
  },
  {
    "name": "fbXZngOw",
    "scores": [
      50
    ]
  },
  {
    "name": "zGDTmiDh",
    "scores": [
      94
    ]
  },
  {
    "name": "qBNIXdP",
    "scores": [
      49,
      29,
      97,
      65
    ]
  },
  {
    "name": "xXdIpg",
    "scores": [
      16,
      61,
      100
    ]
  },
  {
    "name": "otTfvM",
    "scores": [
      85,
      57,
      35,
      15,
      47
    ]
  },
  {
    "name": "VlgYx",
    "scores": [
      0,
      88,
      78,
      85,
      68
    ]
  },
  {
    "name": "aplmcedCf",
    "scores": [
      27,
      57,
      37,
      18
    ]
  },
  {
    "name": "ZXtFnPX",
    "scores": [
      75,
      98,
      27,
      89,
      8
    ]
  },
  {
    "name": "LgPXaR",
    "scores": [
      92,
      70,
      53,
      5,
      45
    ]
  },
  {
    "name": "RoLiGLeoJT",
    "scores": []
  },
  {
    "name": "peBsc",
    "scores": [
      10
    ]
  },
  {
    "name": "zXonKYxx",
    "scores": []
  },
  {
    "name": "xIyfyTc",
    "scores": [
      85,
      58,
      19,
      89
    ]
  },
  {
    "name": "ieTCpNbsjM",
    "scores": [
      87,
      75,
      10
    ]
  },
  {
    "name": "kMgeR",
    "scores": [
      39,
      32
    ]
  },
  {
    "name": "WoXaCfZd",
    "scores": [
      41,
      61,
      39,
      23,
      53
    ]
  },
  {
    "name": "MDiUJ",
    "scores": [
      38,
      99,
      71
    ]
  },
  {
    "name": "zGWHDFP",
    "scores": [
      74,
      0,
      47,
      71
    ]
  },
  {
    "name": "NlcdA",
    "scores": [
      27,
      47
    ]
  },
  {
    "name": "JvYcbo",
    "scores": [
      98,
      22
    ]
  },
  {
    "name": "DuVJqaS",
    "scores": [
      76,
      33,
      70,
      89
    ]
  },
  {
    "name": "XXskVbvEFU",
    "scores": [
      28,
      48,
      31,
      35,
      95
    ]
  },
  {
    "name": "QzXyzUHa",
    "scores": [
      78,
      85,
      16
    ]
  },
  {
    "name": "LajhID",
    "scores": [
      63,
      26,
      19
    ]
  },
  {
    "name": "xqIraQ",
    "scores": [
      57,
      34
    ]
  },
  {
    "name": "eNhMZshAYw",
    "scores": [
      63,
      68,
      31,
      26,
      48
    ]
  },
  {
    "name": "OTGOP",
    "scores": [
      88,
      18
    ]
  },
  {
    "name": "YpaxI",
    "scores": [
      61,
      21,
      78,
      58
    ]
  },
  {
    "name": "eVrkkdqZtt",
    "scores": [
      36,
      26
    ]
  },
  {
    "name": "wWndn",
    "scores": [
      41,
      79,
      74
    ]
  },
  {
    "name": "TxbzRjF",
    "scores": [
      24
    ]
  },
  {
    "name": "gZsfsZOxHr",
    "scores": [
      9,
      38
    ]
  },
  {
    "name": "PXJQkGeYDC",
    "scores": [
      34,
      63,
      80
    ]
  },
  {
    "name": "aWTWGykZET",
    "scores": [
      47,
      63,
      5
    ]
  },
  {
    "name": "CEeRw",
    "scores": [
      22,
      36
    ]
  },
  {
    "name": "OHbJdgF",
    "scores": []
  },
  {
    "name": "nXkOg",
    "scores": []
  },
  {
    "name": "pFrOv",
    "scores": [
      89,
      8,
      17,
      44,
      12
    ]
  },
  {
    "name": "sUWnM",
    "scores": [
      45,
      84
    ]
  },
  {
    "name": "NdVaDaB",
    "scores": [
      16
    ]
  },
  {
    "name": "ZBTeGHJ",
    "scores": [
      88,
      78,
      38,
      24
    ]
  },
  {
    "name": "YDlgkAi",
    "scores": [
      56,
      88,
      48
    ]
  },
  {
    "name": "qpOCYHVcBh",
    "scores": []
  },
  {
    "name": "FTwcn",
    "scores": [
      17
    ]
  },
  {
    "name": "vePES",
    "scores": [
      51,
      42,
      96,
      64
    ]
  },
  {
    "name": "RrlAVRPwb",
    "scores": [
      45
    ]
  },
  {
    "name": "aFXNwpWHVq",
    "scores": [
      88,
      91,
      74,
      62,
      34
    ]
  },
  {
    "name": "qDppLnTKK",
    "scores": [
      29,
      38,
      18,
      65,
      1
    ]
  },
  {
    "name": "dqOiY",
    "scores": [
      27,
      39,
      35
    ]
  },
  {
    "name": "MpEtXACyCZ",
    "scores": [
      98
    ]
  },
  {
    "name": "HlYwpIqPp",
    "scores": []
  },
  {
    "name": "WGPLeXwRMA",
    "scores": [
      79,
      91,
      95,
      33,
      2
    ]
  },
  {
    "name": "fUSCpDJbgx",
    "scores": [
      1,
      84,
      29,
      34,
      7
    ]
  },
  {
    "name": "yxxRwZzET",
    "scores": [
      15
    ]
  },
  {
    "name": "UiecLjgcKd",
    "scores": []
  },
  {
    "name": "nDuhIKOp",
    "scores": []
  },
  {
    "name": "GgFNrH",
    "scores": [
      89,
      11,
      27
    ]
  },
  {
    "name": "KbuwuHLQF",
    "scores": [
      66
    ]
  },
  {
    "name": "oOXUW",
    "scores": [
      52,
      10
    ]
  },
  {
    "name": "ixwXNasYgl",
    "scores": []
  },
  {
    "name": "TqbVsP",
    "scores": []
  },
  {
    "name": "hfEvnbEo",
    "scores": [
      91,
      55,
      27
    ]
  },
  {
    "name": "HVzkK",
    "scores": [
      83,
      32,
      3,
      28,
      84
    ]
  },
  {
    "name": "jwRYRTv",
    "scores": [
      27,
      12,
      60
    ]
  },
  {
    "name": "tdjIYSix",
    "scores": [
      69,
      48,
      94,
      99,
      95
    ]
  },
  {
    "name": "ULVXGXqB",
    "scores": [
      57,
      64,
      16
    ]
  },
  {
    "name": "frFivmxEbH",
    "scores": [
      81
    ]
  },
  {
    "name": "NsBoOxrz",
    "scores": [
      82
    ]
  },
  {
    "name": "AEIpmB",
    "scores": [
      43,
      44,
      17,
      84,
      87
    ]
  },
  {
    "name": "fbTNXrUON",
    "scores": [
      44,
      42,
      11,
      78
    ]
  },
  {
    "name": "TbXOXWhX",
    "scores": [
      68
    ]
  },
  {
    "name": "kysZN",
    "scores": []
  },
  {
    "name": "MwYttQw",
    "scores": [
      81,
      35,
      10
    ]
  },
  {
    "name": "hrXxUHzbF",
    "scores": [
      33,
      12,
      17,
      37,
      24
    ]
  },
  {
    "name": "qlJwl",
    "scores": [
      80
    ]
  },
  {
    "name": "aOpQwS",
    "scores": [
      100,
      59,
      30
    ]
  },
  {
    "name": "BwdRuTUI",
    "scores": [
      39
    ]
  },
  {
    "name": "ntMMiT",
    "scores": [
      41
    ]
  },
  {
    "name": "mgnGOeZn",
    "scores": [
      63,
      31
    ]
  },
  {
    "name": "SvZSfBgLMD",
    "scores": [
      78,
      24,
      55,
      44
    ]
  },
  {
    "name": "yYutlV",
    "scores": [
      19
    ]
  },
  {
    "name": "WvSdXAmq",
    "scores": [
      2,
      41,
      11,
      29,
      63
    ]
  },
  {
    "name": "leQAwDC",
    "scores": [
      32,
      93,
      41
    ]
  },
  {
    "name": "FruAIKi",
    "scores": [
      8,
      69
    ]
  },
  {
    "name": "ZadhSqi",
    "scores": [
      36,
      70
    ]
  },
  {
    "name": "GAuFl",
    "scores": [
      76,
      4,
      9,
      37,
      37
    ]
  },
  {
    "name": "vTvSbhwT",
    "scores": [
      90,
      15,
      5
    ]
  },
  {
    "name": "EyPGWuc",
    "scores": [
      52
    ]
  },
  {
    "name": "BOZWXZXXL",
    "scores": [
      22,
      29,
      5,
      59
    ]
  },
  {
    "name": "ZlYoTtT",
    "scores": [
      84,
      73,
      2,
      39
    ]
  },
  {
    "name": "gCnZUXu",
    "scores": [
      88,
      21,
      76
    ]
  },
  {
    "name": "YVJJosPts",
    "scores": [
      24,
      78,
      95,
      100
    ]
  },
  {
    "name": "uoKPbzTSi",
    "scores": [
      68,
      74,
      81,
      55,
      47
    ]
  },
  {
    "name": "kPwWM",
    "scores": [
      28,
      82
    ]
  },
  {
    "name": "RuOXKXyprZ",
    "scores": [
      28,
      81,
      37,
      92
    ]
  },
  {
    "name": "KYHJcThzdb",
    "scores": [
      13,
      35
    ]
  },
  {
    "name": "yDuQfF",
    "scores": [
      75,
      94,
      81
    ]
  },
  {
    "name": "jQUIdyM",
    "scores": [
      29,
      46,
      97,
      8,
      99
    ]
  },
  {
    "name": "ugSyW",
    "scores": []
  },
  {
    "name": "LRwGBxecS",
    "scores": [
      94,
      41
    ]
  },
  {
    "name": "PSzEVXul",
    "scores": [
      89,
      63
    ]
  },
  {
    "name": "qROFwXh",
    "scores": []
  },
  {
    "name": "dsejAGoOZ",
    "scores": [
      16
    ]
  },
  {
    "name": "CKamKON",
    "scores": [
      44,
      86,
      56,
      57
    ]
  },
  {
    "name": "bDTOkf",
    "scores": [
      23,
      25,
      68,
      64,
      51
    ]
  },
  {
    "name": "LsJXYq",
    "scores": [
      68,
      11,
      1,
      9,
      34
    ]
  },
  {
    "name": "BJYtc",
    "scores": [
      6
    ]
  },
  {
    "name": "EZehKNj",
    "scores": [
      73,
      33,
      61
    ]
  },
  {
    "name": "JYDeMo",
    "scores": [
      89,
      38
    ]
  },
  {
    "name": "ICCSPShba",
    "scores": []
  },
  {
    "name": "blKnZybxH",
    "scores": [
      87,
      68
    ]
  },
  {
    "name": "VgRwZQola",
    "scores": []
  },
  {
    "name": "ndbxWBqDct",
    "scores": [
      62,
      25
    ]
  },
  {
    "name": "TYCPZ",
    "scores": [
      51,
      5,
      29,
      45,
      66
    ]
  },
  {
    "name": "QwVCQ",
    "scores": [
      85
    ]
  },
  {
    "name": "LxMxh",
    "scores": [
      45,
      63,
      12,
      82
    ]
  },
  {
    "name": "BPXzlP",
    "scores": []
  },
  {
    "name": "CEzLkVLA",
    "scores": [
      1,
      93,
      64
    ]
  },
  {
    "name": "GmWKIZxTp",
    "scores": [
      85,
      49,
      33,
      34
    ]
  },
  {
    "name": "IxSuyANBCz",
    "scores": [
      33,
      89,
      49,
      50,
      49
    ]
  },
  {
    "name": "nbYWHfbCq",
    "scores": [
      0,
      39
    ]
  },
  {
    "name": "RmNaUbHR",
    "scores": [
      99,
      73,
      75
    ]
  },
  {
    "name": "raSKYUv",
    "scores": []
  },
  {
    "name": "hszZvxI",
    "scores": [
      0,
      8,
      66,
      86,
      70
    ]
  },
  {
    "name": "JQgrQl",
    "scores": [
      33,
      4,
      25,
      60
    ]
  },
  {
    "name": "BbnhUSYgt",
    "scores": []
  },
  {
    "name": "NblYbNVAL",
    "scores": [
      99
    ]
  },
  {
    "name": "RpNASD",
    "scores": [
      34
    ]
  },
  {
    "name": "KPjVQWD",
    "scores": [
      72,
      61
    ]
  },
  {
    "name": "aTcAzQ",
    "scores": [
      59,
      7
    ]
  },
  {
    "name": "rTWLiMB",
    "scores": [
      77,
      53,
      9
    ]
  },
  {
    "name": "sBdosC",
    "scores": [
      9,
      55
    ]
  },
  {
    "name": "SpACrVgu",
    "scores": [
      11,
      41,
      78,
      66,
      36
    ]
  },
  {
    "name": "FarZbltC",
    "scores": [
      10
    ]
  },
  {
    "name": "YwGnOiNS",
    "scores": [
      68,
      54
    ]
  },
  {
    "name": "fEKjUDhy",
    "scores": [
      54,
      23,
      55
    ]
  },
  {
    "name": "hiAEBzpnk",
    "scores": [
      83,
      85
    ]
  },
  {
    "name": "AVgmJiCO",
    "scores": [
      33,
      41,
      56,
      90
    ]
  },
  {
    "name": "YQuhKy",
    "scores": [
      46,
      87
    ]
  },
  {
    "name": "fYAwebuSJq",
    "scores": [
      71,
      22,
      91,
      8,
      45
    ]
  },
  {
    "name": "WgOywI",
    "scores": [
      89,
      45,
      33
    ]
  },
  {
    "name": "KqdmZ",
    "scores": [
      10,
      78,
      98,
      88,
      38
    ]
  },
  {
    "name": "nQjtOu",
    "scores": [
      10,
      75,
      97,
      39,
      97
    ]
  },
  {
    "name": "gZAlS",
    "scores": [
      59,
      4,
      73,
      99,
      8
    ]
  },
  {
    "name": "ODZRO",
    "scores": []
  },
  {
    "name": "DNurFZJH",
    "scores": [
      16,
      7,
      35
    ]
  },
  {
    "name": "eFGvFgdz",
    "scores": []
  },
  {
    "name": "heMKodrvVj",
    "scores": [
      94
    ]
  },
  {
    "name": "rPXWlaEdoP",
    "scores": [
      14,
      100
    ]
  },
  {
    "name": "aWyZmqqNu",
    "scores": []
  },
  {
    "name": "wLmTx",
    "scores": [
      25,
      3
    ]
  },
  {
    "name": "LvbzBC",
    "scores": [
      71,
      9
    ]
  },
  {
    "name": "xOwGGk",
    "scores": []
  },
  {
    "name": "lSotiaCYH",
    "scores": [
      42,
      77
    ]
  },
  {
    "name": "XXmZCjuv",
    "scores": [
      24,
      52
    ]
  },
  {
    "name": "ETFKvkJnLv",
    "scores": [
      83,
      71,
      47,
      8
    ]
  },
  {
    "name": "zFTXBR",
    "scores": [
      0,
      52,
      57,
      75,
      23
    ]
  },
  {
    "name": "WwPHpPrenG",
    "scores": [
      79,
      51,
      47,
      72,
      2
    ]
  },
  {
    "name": "gDLSFJkbz",
    "scores": [
      76,
      93,
      7,
      80,
      4
    ]
  },
  {
    "name": "onWrUYrzh",
    "scores": []
  },
  {
    "name": "OPDFr",
    "scores": [
      3
    ]
  },
  {
    "name": "GUXWoNbjU",
    "scores": [
      73,
      89
    ]
  },
  {
    "name": "GKvogCFCcG",
    "scores": []
  },
  {
    "name": "YlQLh",
    "scores": []
  },
  {
    "name": "icQYfcCedd",
    "scores": [
      43
    ]
  },
  {
    "name": "vdweaOamo",
    "scores": []
  },
  {
    "name": "UuoZnYN",
    "scores": [
      69,
      88,
      52,
      5,
      24
    ]
  },
  {
    "name": "qXaRSPSU",
    "scores": [
      31,
      67,
      75,
      44,
      61
    ]
  },
  {
    "name": "wlvLWtNUlD",
    "scores": [
      75,
      36,
      55,
      8
    ]
  },
  {
    "name": "FSReaUosgl",
    "scores": [
      49
    ]
  },
  {
    "name": "bUieUbuGCY",
    "scores": [
      10,
      10,
      6,
      97
    ]
  },
  {
    "name": "lwQokc",
    "scores": [
      54,
      60,
      1
    ]
  },
  {
    "name": "FLVSGyJy",
    "scores": [
      91,
      93,
      76,
      8
    ]
  },
  {
    "name": "RGNLXRVHJK",
    "scores": [
      2,
      55
    ]
  },
  {
    "name": "FIjChh",
    "scores": [
      6,
      62
    ]
  },
  {
    "name": "cUYGfbB",
    "scores": [
      33
    ]
  },
  {
    "name": "WvvQUkzb",
    "scores": [
      61,
      35,
      16
    ]
  },
  {
    "name": "jmSeInEs",
    "scores": [
      26,
      21,
      81,
      69,
      52
    ]
  },
  {
    "name": "DeRLgB",
    "scores": [
      69,
      19,
      13,
      35,
      50
    ]
  },
  {
    "name": "GtcLUEX",
    "scores": [
      93,
      81,
      57
    ]
  },
  {
    "name": "RoptRSc",
    "scores": [
      56,
      45,
      78
    ]
  },
  {
    "name": "zVeeePZu",
    "scores": [
      68,
      35
    ]
  },
  {
    "name": "fisqqsFX",
    "scores": [
      17
    ]
  },
  {
    "name": "aRuzAaMp",
    "scores": [
      99,
      34,
      92,
      91,
      67
    ]
  },
  {
    "name": "rzArEN",
    "scores": [
      87,
      22,
      76
    ]
  },
  {
    "name": "wIekSw",
    "scores": [
      71,
      80
    ]
  },
  {
    "name": "gnvxAF",
    "scores": [
      54,
      2,
      66
    ]
  },
  {
    "name": "JIFFUmNwG",
    "scores": [
      18
    ]
  },
  {
    "name": "TpYmkUdb",
    "scores": []
  },
  {
    "name": "IAbpeKuxym",
    "scores": []
  },
  {
    "name": "MnTZgJfcWz",
    "scores": [
      44
    ]
  },
  {
    "name": "ItuFzcJ",
    "scores": [
      59,
      5,
      98
    ]
  },
  {
    "name": "BrwyyxT",
    "scores": [
      14,
      29
    ]
  },
  {
    "name": "UkJBpUZLU",
    "scores": [
      28,
      65
    ]
  },
  {
    "name": "xfjxaaamL",
    "scores": [
      67,
      41,
      82,
      6
    ]
  },
  {
    "name": "dRkKSYGd",
    "scores": [
      88,
      84,
      45,
      72
    ]
  },
  {
    "name": "jDTBe",
    "scores": [
      76,
      25,
      52,
      9,
      59
    ]
  },
  {
    "name": "MNTcNscueb",
    "scores": [
      3,
      31,
      58
    ]
  },
  {
    "name": "GeWNnWOHpe",
    "scores": [
      6,
      45,
      30,
      11
    ]
  },
  {
    "name": "uSvqMIo",
    "scores": [
      97,
      66,
      17,
      21,
      49
    ]
  },
  {
    "name": "frKXkSYiEd",
    "scores": [
      99,
      21,
      51,
      53,
      72
    ]
  },
  {
    "name": "wMjdP",
    "scores": [
      99,
      47,
      21
    ]
  },
  {
    "name": "FkCDl",
    "scores": []
  },
  {
    "name": "ZVEjC",
    "scores": [
      64,
      54,
      32,
      95
    ]
  },
  {
    "name": "cTAPnn",
    "scores": [
      79,
      90,
      15
    ]
  },
  {
    "name": "Epdis",
    "scores": []
  },
  {
    "name": "pmLpqhC",
    "scores": [
      42,
      71,
      19,
      82
    ]
  },
  {
    "name": "NsDGb",
    "scores": [
      11,
      67,
      6,
      56
    ]
  },
  {
    "name": "XhMZIKvMrq",
    "scores": [
      25,
      39
    ]
  },
  {
    "name": "MOdexaPbAd",
    "scores": [
      93
    ]
  },
  {
    "name": "wjUqNoB",
    "scores": [
      78,
      13,
      80,
      25
    ]
  },
  {
    "name": "Ulzpqnion",
    "scores": []
  },
  {
    "name": "twtuD",
    "scores": [
      98,
      39,
      100,
      23
    ]
  },
  {
    "name": "wtcvErGhk",
    "scores": [
      94,
      66
    ]
  },
  {
    "name": "SzQdfLqIP",
    "scores": [
      39,
      13,
      32
    ]
  },
  {
    "name": "rXFse",
    "scores": [
      28,
      10,
      51,
      97
    ]
  },
  {
    "name": "ObmPdCt",
    "scores": []
  },
  {
    "name": "CuwKlX",
    "scores": [
      100,
      96,
      45
    ]
  },
  {
    "name": "GKWedw",
    "scores": [
      24
    ]
  },
  {
    "name": "HuutAgFmZ",
    "scores": []
  },
  {
    "name": "DhIkd",
    "scores": []
  },
  {
    "name": "mMuhS",
    "scores": [
      21,
      81
    ]
  },
  {
    "name": "PDRIi",
    "scores": []
  },
  {
    "name": "FbPKa",
    "scores": [
      39
    ]
  },
  {
    "name": "vMeoDYqHpf",
    "scores": [
      6,
      57,
      42,
      80
    ]
  },
  {
    "name": "hkgof",
    "scores": [
      48,
      22,
      26,
      63,
      55
    ]
  },
  {
    "name": "cccceK",
    "scores": [
      29,
      63,
      17,
      47
    ]
  },
  {
    "name": "LJLpNI",
    "scores": [
      18,
      51,
      32
    ]
  },
  {
    "name": "wksZfc",
    "scores": [
      22,
      82,
      8,
      40
    ]
  },
  {
    "name": "WIUtRJKhQ",
    "scores": [
      62,
      51
    ]
  },
  {
    "name": "KbRplGs",
    "scores": [
      94,
      66,
      91,
      66,
      27
    ]
  },
  {
    "name": "KMEZUz",
    "scores": [
      40
    ]
  },
  {
    "name": "hMKiQ",
    "scores": [
      17,
      15,
      4,
      10
    ]
  },
  {
    "name": "Qkdqdk",
    "scores": [
      36,
      78,
      89
    ]
  },
  {
    "name": "klgGQBhx",
    "scores": []
  },
  {
    "name": "xyQzt",
    "scores": [
      8,
      81
    ]
  },
  {
    "name": "WbVfl",
    "scores": [
      42,
      22,
      35
    ]
  },
  {
    "name": "dOpajUH",
    "scores": [
      10
    ]
  },
  {
    "name": "MilraiPG",
    "scores": [
      33,
      34,
      18
    ]
  },
  {
    "name": "fgipMlxlIX",
    "scores": [
      68,
      14,
      86,
      80,
      99
    ]
  },
  {
    "name": "KmNBOGp",
    "scores": [
      2,
      19,
      51,
      62
    ]
  },
  {
    "name": "tkHzsFisMx",
    "scores": [
      98
    ]
  },
  {
    "name": "SamyWdzGg",
    "scores": [
      71,
      5
    ]
  },
  {
    "name": "MgFZWWKo",
    "scores": [
      97,
      58,
      9
    ]
  },
  {
    "name": "DVJGuCg",
    "scores": [
      81,
      25
    ]
  },
  {
    "name": "MPCmsm",
    "scores": []
  },
  {
    "name": "JEOyyo",
    "scores": [
      37,
      15
    ]
  },
  {
    "name": "jBvfcLxfo",
    "scores": [
      72
    ]
  },
  {
    "name": "RGQWa",
    "scores": []
  },
  {
    "name": "HzeWPCH",
    "scores": [
      10,
      81
    ]
  },
  {
    "name": "oHvfVWRUyV",
    "scores": []
  },
  {
    "name": "AZOMaqLu",
    "scores": [
      10,
      27,
      65,
      68,
      26
    ]
  },
  {
    "name": "ezzyctytHN",
    "scores": [
      44,
      54,
      73,
      69,
      7
    ]
  },
  {
    "name": "EyIscs",
    "scores": [
      32,
      16,
      78
    ]
  },
  {
    "name": "Tjliss",
    "scores": [
      75,
      79,
      45,
      82,
      15
    ]
  },
  {
    "name": "CVdBcB",
    "scores": [
      61,
      5,
      11,
      48,
      86
    ]
  },
  {
    "name": "EzexdxEqe",
    "scores": [
      54
    ]
  },
  {
    "name": "RcoCbRUVM",
    "scores": [
      91,
      13,
      81
    ]
  },
  {
    "name": "KXsitXVxA",
    "scores": [
      22
    ]
  },
  {
    "name": "SHPdr",
    "scores": [
      97,
      66,
      54
    ]
  },
  {
    "name": "ADNHKUhG",
    "scores": [
      99
    ]
  },
  {
    "name": "EboDoLq",
    "scores": []
  },
  {
    "name": "rWfQFHX",
    "scores": [
      59
    ]
  },
  {
    "name": "nHpuzpK",
    "scores": []
  },
  {
    "name": "rgQRt",
    "scores": [
      5,
      5
    ]
  },
  {
    "name": "mykmb",
    "scores": []
  },
  {
    "name": "KJPDUO",
    "scores": [
      81,
      12
    ]
  },
  {
    "name": "PiuvDDa",
    "scores": [
      39,
      53
    ]
  },
  {
    "name": "mGBUVQR",
    "scores": []
  },
  {
    "name": "gHsmDuxtiA",
    "scores": [
      79,
      87,
      77,
      3,
      62
    ]
  },
  {
    "name": "nCBgXtLn",
    "scores": []
  },
  {
    "name": "zSOpcQyz",
    "scores": [
      62
    ]
  },
  {
    "name": "CIwqrGFDtC",
    "scores": [
      92,
      20,
      98
    ]
  },
  {
    "name": "bILmuHksu",
    "scores": [
      98,
      32,
      93,
      61
    ]
  },
  {
    "name": "OBzcUiAM",
    "scores": [
      10,
      62,
      100
    ]
  },
  {
    "name": "RxeWTqHJJH",
    "scores": [
      85
    ]
  },
  {
    "name": "jeAngOgn",
    "scores": [
      40,
      63,
      56,
      88
    ]
  },
  {
    "name": "fzQMDNioid",
    "scores": [
      91,
      34,
      50,
      22
    ]
  },
  {
    "name": "ZFulPDsFjG",
    "scores": [
      33,
      20,
      3,
      40
    ]
  },
  {
    "name": "VXlzYhjRv",
    "scores": [
      22,
      39,
      0
    ]
  },
  {
    "name": "FjaYTiBI",
    "scores": []
  },
  {
    "name": "XjaEj",
    "scores": [
      14,
      11
    ]
  },
  {
    "name": "fjfOYFqe",
    "scores": [
      84,
      50,
      25,
      4
    ]
  },
  {
    "name": "IYoCYVn",
    "scores": [
      43,
      11
    ]
  },
  {
    "name": "PHUjqEVe",
    "scores": [
      67,
      93,
      93
    ]
  },
  {
    "name": "feaLsyORz",
    "scores": [
      44,
      97,
      73,
      73,
      64
    ]
  },
  {
    "name": "DjmkyzQQk",
    "scores": []
  },
  {
    "name": "kEPVteDKdB",
    "scores": []
  },
  {
    "name": "FouTYwN",
    "scores": []
  },
  {
    "name": "IuKSpEy",
    "scores": [
      72,
      75,
      62,
      70
    ]
  },
  {
    "name": "imSuHhfoW",
    "scores": [
      53,
      16,
      40,
      47,
      49
    ]
  },
  {
    "name": "EZtimeKr",
    "scores": [
      3,
      87,
      63,
      91,
      42
    ]
  },
  {
    "name": "uGolI",
    "scores": []
  },
  {
    "name": "jaGJcgn",
    "scores": []
  },
  {
    "name": "uIciDvBU",
    "scores": [
      99,
      53
    ]
  },
  {
    "name": "ATKHG",
    "scores": [
      78,
      24,
      13
    ]
  },
  {
    "name": "MmpNO",
    "scores": [
      48,
      36,
      91
    ]
  },
  {
    "name": "GZXmRtiDdD",
    "scores": [
      0,
      19
    ]
  },
  {
    "name": "OpGNQS",
    "scores": [
      72,
      90,
      85
    ]
  },
  {
    "name": "TdVnj",
    "scores": [
      27,
      11,
      100
    ]
  },
  {
    "name": "DKUIuHa",
    "scores": [
      12,
      43,
      79,
      78,
      92
    ]
  },
  {
    "name": "bGBDGZ",
    "scores": [
      57,
      71,
      74,
      24
    ]
  },
  {
    "name": "mSuEIwjvx",
    "scores": [
      68,
      99,
      16
    ]
  },
  {
    "name": "zKYHiQd",
    "scores": [
      39
    ]
  },
  {
    "name": "WjJrbJoI",
    "scores": [
      68,
      86,
      11,
      78,
      95
    ]
  },
  {
    "name": "QtppT",
    "scores": []
  },
  {
    "name": "RqgWnfXr",
    "scores": []
  },
  {
    "name": "aIFbr",
    "scores": [
      84,
      39,
      9,
      91
    ]
  },
  {
    "name": "taomlIM",
    "scores": []
  },
  {
    "name": "rMKMarw",
    "scores": [
      34,
      66,
      39,
      80
    ]
  },
  {
    "name": "fvKMqZi",
    "scores": [
      63,
      15,
      88
    ]
  },
  {
    "name": "xIBcyffnD",
    "scores": [
      95,
      79,
      53
    ]
  },
  {
    "name": "DOSOwiL",
    "scores": [
      62,
      25,
      35,
      51
    ]
  },
  {
    "name": "hlgLwjAmtU",
    "scores": [
      50
    ]
  },
  {
    "name": "oOAVuRwRqB",
    "scores": [
      87,
      84,
      10,
      1
    ]
  },
  {
    "name": "SqeKI",
    "scores": [
      31,
      87,
      59,
      17
    ]
  },
  {
    "name": "Pkyyknqs",
    "scores": []
  },
  {
    "name": "Ioqhr",
    "scores": [
      94,
      6
    ]
  },
  {
    "name": "ZmPKVPN",
    "scores": [
      25
    ]
  },
  {
    "name": "pqXnBUgk",
    "scores": [
      9,
      57,
      58,
      41,
      27
    ]
  },
  {
    "name": "rjgYtT",
    "scores": []
  },
  {
    "name": "IkzKyRoC",
    "scores": [
      97,
      22,
      61,
      15
    ]
  },
  {
    "name": "lAzQIkC",
    "scores": []
  },
  {
    "name": "AyTMdB",
    "scores": [
      94,
      88
    ]
  },
  {
    "name": "MUPShKBB",
    "scores": [
      20,
      6,
      99,
      18,
      34
    ]
  },
  {
    "name": "DImyYj",
    "scores": []
  },
  {
    "name": "OYgYoZK",
    "scores": [
      2
    ]
  },
  {
    "name": "wjpnHlyM",
    "scores": [
      87,
      2,
      27,
      1,
      80
    ]
  },
  {
    "name": "PtQndCOqwo",
    "scores": []
  },
  {
    "name": "VVhCQf",
    "scores": [
      77,
      66,
      59
    ]
  },
  {
    "name": "rephfgoQ",
    "scores": []
  },
  {
    "name": "EoySTuofQa",
    "scores": [
      94,
      30,
      16
    ]
  },
  {
    "name": "qGEorAb",
    "scores": [
      1,
      99
    ]
  },
  {
    "name": "frGJLbi",
    "scores": [
      98
    ]
  },
  {
    "name": "ouFhlyiTJ",
    "scores": [
      27
    ]
  },
  {
    "name": "xAZqMd",
    "scores": []
  },
  {
    "name": "vqvDCWX",
    "scores": [
      96,
      85,
      53
    ]
  },
  {
    "name": "WSvjXrpRO",
    "scores": [
      12,
      61,
      51,
      89,
      0
    ]
  },
  {
    "name": "GYAoU",
    "scores": []
  },
  {
    "name": "xDkIzV",
    "scores": [
      31,
      69
    ]
  },
  {
    "name": "MGBgzgNyDz",
    "scores": [
      7,
      31,
      2
    ]
  },
  {
    "name": "XYoMW",
    "scores": [
      70,
      4
    ]
  },
  {
    "name": "zZEQhzma",
    "scores": [
      3,
      96
    ]
  },
  {
    "name": "nMymJGjP",
    "scores": [
      87,
      69,
      54
    ]
  },
  {
    "name": "NJwpUstUyM",
    "scores": [
      6,
      19,
      12
    ]
  },
  {
    "name": "iJJZYKE",
    "scores": [
      57
    ]
  },
  {
    "name": "oeyclDtVA",
    "scores": [
      28
    ]
  },
  {
    "name": "zSnra",
    "scores": [
      74
    ]
  },
  {
    "name": "CErSRulpc",
    "scores": [
      6,
      87,
      81
    ]
  },
  {
    "name": "guEaXhIHwh",
    "scores": [
      41,
      69,
      10,
      51
    ]
  },
  {
    "name": "vXuFQ",
    "scores": []
  },
  {
    "name": "tQTHokUm",
    "scores": [
      12,
      2,
      49
    ]
  },
  {
    "name": "upPxsRiAa",
    "scores": []
  },
  {
    "name": "mLdMu",
    "scores": [
      49,
      27,
      54,
      0
    ]
  },
  {
    "name": "NfobzRLck",
    "scores": [
      9,
      73,
      14,
      51,
      26
    ]
  },
  {
    "name": "OScEsn",
    "scores": [
      43,
      62,
      47,
      60
    ]
  },
  {
    "name": "qjOugLLGt",
    "scores": [
      50,
      9
    ]
  },
  {
    "name": "fkeLv",
    "scores": [
      88,
      51,
      53
    ]
  },
  {
    "name": "xQxKOIMbXv",
    "scores": [
      73,
      3,
      97
    ]
  },
  {
    "name": "AYUnrH",
    "scores": [
      86
    ]
  },
  {
    "name": "pQWjeqylvV",
    "scores": []
  },
  {
    "name": "OzunUB",
    "scores": [
      90,
      66,
      11,
      62
    ]
  },
  {
    "name": "NPxWqwvA",
    "scores": [
      26,
      37
    ]
  },
  {
    "name": "noiso",
    "scores": [
      66,
      16
    ]
  },
  {
    "name": "epvCSnci",
    "scores": [
      26,
      52
    ]
  },
  {
    "name": "uhCpZ",
    "scores": [
      0,
      48,
      71
    ]
  },
  {
    "name": "oSemDCFN",
    "scores": [
      92,
      61
    ]
  },
  {
    "name": "HjzQduJvem",
    "scores": [
      34,
      44,
      52
    ]
  },
  {
    "name": "gIEplzG",
    "scores": [
      81
    ]
  },
  {
    "name": "ExWHZLi",
    "scores": [
      30,
      29,
      50,
      88
    ]
  },
  {
    "name": "MYreQeT",
    "scores": [
      51,
      92,
      92,
      62,
      28
    ]
  },
  {
    "name": "iZQlbxthns",
    "scores": [
      93,
      55
    ]
  },
  {
    "name": "ThYKtzRcvr",
    "scores": [
      51,
      70
    ]
  },
  {
    "name": "bPfPIJNwVV",
    "scores": [
      39,
      32
    ]
  },
  {
    "name": "zpTAKCHw",
    "scores": [
      39,
      88
    ]
  },
  {
    "name": "GwYpJDoKeG",
    "scores": [
      33,
      49,
      23,
      97,
      62
    ]
  },
  {
    "name": "WeUsLNSk",
    "scores": [
      38,
      97,
      80,
      97,
      18
    ]
  },
  {
    "name": "oMRBNP",
    "scores": [
      65,
      72,
      59,
      2
    ]
  },
  {
    "name": "UPAmvPXtoL",
    "scores": [
      100,
      10
    ]
  },
  {
    "name": "irMkmfDTnN",
    "scores": []
  },
  {
    "name": "oFEoeJWpX",
    "scores": [
      35,
      38,
      24,
      2
    ]
  },
  {
    "name": "AXzey",
    "scores": []
  },
  {
    "name": "oQXwo",
    "scores": [
      99,
      95,
      66,
      2
    ]
  },
  {
    "name": "sVPUW",
    "scores": [
      85,
      45,
      95,
      67,
      28
    ]
  },
  {
    "name": "PcgoUbo",
    "scores": [
      68,
      1,
      49,
      65
    ]
  },
  {
    "name": "KKYotWPi",
    "scores": [
      16,
      7,
      5
    ]
  },
  {
    "name": "zOgfuwpan",
    "scores": []
  },
  {
    "name": "MPwbUqukW",
    "scores": [
      75,
      56,
      46,
      79
    ]
  },
  {
    "name": "fUvGjofC",
    "scores": [
      75,
      13,
      8
    ]
  },
  {
    "name": "lXRjjT",
    "scores": []
  },
  {
    "name": "pasiyt",
    "scores": []
  },
  {
    "name": "lWaEUjqk",
    "scores": [
      22
    ]
  },
  {
    "name": "XOKQkjdnsH",
    "scores": []
  },
  {
    "name": "hbrTQ",
    "scores": [
      20
    ]
  },
  {
    "name": "CuSzKguE",
    "scores": [
      70,
      1,
      73,
      74,
      38
    ]
  },
  {
    "name": "UrwgZdj",
    "scores": [
      58
    ]
  },
  {
    "name": "ogsdiw",
    "scores": []
  },
  {
    "name": "RdSQzQLHpA",
    "scores": [
      43,
      19
    ]
  },
  {
    "name": "uWncVpo",
    "scores": []
  },
  {
    "name": "bGbraKxXEt",
    "scores": [
      69,
      93,
      67
    ]
  },
  {
    "name": "mxEpUZmQ",
    "scores": [
      30,
      24,
      83,
      25
    ]
  },
  {
    "name": "NABMCX",
    "scores": [
      17,
      50
    ]
  },
  {
    "name": "OkgGoKGZp",
    "scores": [
      42,
      42,
      36
    ]
  },
  {
    "name": "xCDjqMSAPE",
    "scores": [
      7
    ]
  },
  {
    "name": "IzUacEPUVs",
    "scores": []
  },
  {
    "name": "SuvDzOYtN",
    "scores": [
      19,
      0
    ]
  },
  {
    "name": "NbAWULagvM",
    "scores": [
      26,
      65,
      66,
      24,
      68
    ]
  },
  {
    "name": "vZCnnKkL",
    "scores": [
      63
    ]
  },
  {
    "name": "KmUur",
    "scores": [
      57,
      16,
      13
    ]
  },
  {
    "name": "JoxPcHrIzJ",
    "scores": []
  },
  {
    "name": "lKIrlJCdb",
    "scores": [
      100,
      93,
      70,
      63,
      59
    ]
  },
  {
    "name": "kDcagq",
    "scores": [
      34,
      95,
      67,
      79
    ]
  },
  {
    "name": "DUyYM",
    "scores": [
      63,
      28,
      12,
      68
    ]
  },
  {
    "name": "LLHjYbb",
    "scores": [
      2
    ]
  },
  {
    "name": "xFapnRWgr",
    "scores": [
      4,
      3,
      49
    ]
  },
  {
    "name": "ZSyDs",
    "scores": [
      91,
      100,
      5,
      39,
      89
    ]
  },
  {
    "name": "CgZBFB",
    "scores": []
  },
  {
    "name": "sWRLCXrl",
    "scores": [
      29
    ]
  },
  {
    "name": "YJjLJcJms",
    "scores": [
      35,
      100,
      28
    ]
  },
  {
    "name": "iODChdLlyN",
    "scores": [
      97,
      47,
      62
    ]
  },
  {
    "name": "SNdrOoza",
    "scores": [
      97,
      71,
      83
    ]
  },
  {
    "name": "zuWEIvFR",
    "scores": []
  },
  {
    "name": "xfRWPcXSy",
    "scores": []
  },
  {
    "name": "ZNaOpxdhN",
    "scores": [
      41,
      54
    ]
  },
  {
    "name": "xDEDVvnm",
    "scores": [
      67,
      8
    ]
  },
  {
    "name": "RDOjfcegzv",
    "scores": [
      70,
      75
    ]
  },
  {
    "name": "kUfxiABItN",
    "scores": [
      24,
      11
    ]
  },
  {
    "name": "EbStgdoO",
    "scores": []
  },
  {
    "name": "JfIxH",
    "scores": [
      49,
      64,
      95
    ]
  },
  {
    "name": "sqcSV",
    "scores": [
      85,
      88,
      69,
      24
    ]
  },
  {
    "name": "bQtRzf",
    "scores": [
      5,
      52,
      90,
      26
    ]
  },
  {
    "name": "bBNcxYLH",
    "scores": [
      97,
      59,
      15
    ]
  },
  {
    "name": "vuHIBdd",
    "scores": [
      93,
      17,
      23,
      17
    ]
  },
  {
    "name": "szyVC",
    "scores": [
      72,
      57,
      9,
      11
    ]
  },
  {
    "name": "NjmRv",
    "scores": [
      22,
      68,
      50
    ]
  },
  {
    "name": "ngzkey",
    "scores": [
      41,
      21
    ]
  },
  {
    "name": "FizifgEU",
    "scores": []
  },
  {
    "name": "nesgdjMrp",
    "scores": [
      21,
      44,
      52,
      55
    ]
  },
  {
    "name": "kCHIl",
    "scores": [
      22,
      82,
      29,
      94
    ]
  },
  {
    "name": "rusMNVqjqI",
    "scores": []
  },
  {
    "name": "auZmIxKUES",
    "scores": [
      16,
      97
    ]
  },
  {
    "name": "tEVwJSsG",
    "scores": [
      52,
      42,
      37
    ]
  },
  {
    "name": "YxahADgZW",
    "scores": [
      1,
      37,
      84
    ]
  },
  {
    "name": "iYXOHcgL",
    "scores": [
      12,
      32,
      52,
      46
    ]
  },
  {
    "name": "fpClLNXex",
    "scores": [
      80,
      64,
      83
    ]
  },
  {
    "name": "lyrkDJrGv",
    "scores": []
  },
  {
    "name": "MLkqhgLBiq",
    "scores": [
      99,
      84,
      89,
      6
    ]
  },
  {
    "name": "svSGdwRNRB",
    "scores": [
      31,
      27,
      95,
      60,
      41
    ]
  },
  {
    "name": "fgNVFgjAh",
    "scores": []
  },
  {
    "name": "IIxopdH",
    "scores": []
  },
  {
    "name": "JnhPe",
    "scores": [
      71,
      71,
      84,
      15,
      67
    ]
  },
  {
    "name": "mbvmJLPZ",
    "scores": [
      99
    ]
  },
  {
    "name": "CwYJhNj",
    "scores": []
  },
  {
    "name": "xupMOVC",
    "scores": [
      14,
      50,
      30
    ]
  },
  {
    "name": "lMYUhpFrR",
    "scores": [
      56,
      86
    ]
  },
  {
    "name": "GewveRoPoy",
    "scores": [
      67,
      99
    ]
  },
  {
    "name": "SEVkUwHiLI",
    "scores": []
  },
  {
    "name": "WTOFtgYLsB",
    "scores": [
      23,
      61,
      80
    ]
  },
  {
    "name": "ncAuAc",
    "scores": []
  },
  {
    "name": "jDzcYCiGWn",
    "scores": [
      19,
      100,
      32
    ]
  },
  {
    "name": "ZbeOIjl",
    "scores": [
      99,
      67,
      86,
      0,
      56
    ]
  },
  {
    "name": "eZgphWh",
    "scores": [
      83,
      71,
      71
    ]
  },
  {
    "name": "qmeyyDOQP",
    "scores": [
      7,
      39
    ]
  },
  {
    "name": "TgUBFO",
    "scores": [
      31
    ]
  },
  {
    "name": "bHvZvH",
    "scores": [
      74,
      71
    ]
  },
  {
    "name": "MAtbFpVT",
    "scores": [
      87,
      87
    ]
  },
  {
    "name": "UofMsprlo",
    "scores": [
      51,
      57
    ]
  },
  {
    "name": "OMHOK",
    "scores": [
      63
    ]
  },
  {
    "name": "tmcYh",
    "scores": [
      12,
      82
    ]
  },
  {
    "name": "AomcvB",
    "scores": [
      65,
      24,
      56,
      89,
      98
    ]
  },
  {
    "name": "dcgrgPfIdn",
    "scores": [
      76,
      50,
      78,
      63
    ]
  },
  {
    "name": "shZrzJKxt",
    "scores": [
      66
    ]
  },
  {
    "name": "XaeabsUs",
    "scores": [
      66,
      40
    ]
  },
  {
    "name": "DIKtBzRRU",
    "scores": []
  },
  {
    "name": "DalovZEBWR",
    "scores": [
      28,
      1,
      86
    ]
  },
  {
    "name": "KXwdEhNKQ",
    "scores": []
  },
  {
    "name": "DapNTxmStP",
    "scores": []
  },
  {
    "name": "XYhnEqj",
    "scores": [
      29
    ]
  },
  {
    "name": "LDadQII",
    "scores": [
      94,
      12,
      51
    ]
  },
  {
    "name": "kMUVov",
    "scores": [
      51,
      67,
      26,
      4,
      83
    ]
  },
  {
    "name": "UEXPd",
    "scores": [
      84,
      44,
      74,
      12,
      44
    ]
  },
  {
    "name": "UIATWTnYl",
    "scores": [
      13,
      87
    ]
  },
  {
    "name": "FMChBuwZeh",
    "scores": [
      65,
      91,
      61
    ]
  },
  {
    "name": "PAXNs",
    "scores": []
  },
  {
    "name": "wWbVyDDj",
    "scores": [
      11,
      97,
      91,
      9,
      41
    ]
  }
]